server_config_generator/__init__.py
server_config_generator/coloured_sys_out.py
server_config_generator/management/__init__.py
server_config_generator/management/commands/__init__.py
server_config_generator/management/commands/generate_apache_config.py
server_config_generator/templates/apache/apache_http_only.tmpl
server_config_generator/templates/apache/apache_https_with_redirect.tmpl
server_config_generator/templates/apache/apache_https_without_redirect.tmpl
django_server_config_generator-1.0.0.dist-info/LICENSE
django_server_config_generator-1.0.0.dist-info/METADATA
django_server_config_generator-1.0.0.dist-info/WHEEL
django_server_config_generator-1.0.0.dist-info/top_level.txt
django_server_config_generator-1.0.0.dist-info/RECORD
