Metadata-Version: 2.1
Name: django-server-config-generator
Version: 1.0.0
Summary: A simple Django app to create server config
Home-page: https://github.com/Afsal-qburst/django-server-config-generator
Author: Afsal Salim
Author-email: afsals@qburst.com
License: UNKNOWN
Platform: UNKNOWN
Classifier: Environment :: Web Environment
Classifier: Framework :: Django
Classifier: Intended Audience :: Developers
Classifier: Operating System :: OS Independent
Classifier: Programming Language :: Python
Classifier: Programming Language :: Python :: 3.6
Classifier: License :: OSI Approved :: MIT License
Requires-Python: >=3.6
